mar_eval-0.1.1.dist-info/licenses/LICENSE
mareval/__init__.py
mareval/cho.py
mareval/stats.py
mareval/utils.py
mar_eval-0.1.1.dist-info/METADATA
mar_eval-0.1.1.dist-info/WHEEL
mar_eval-0.1.1.dist-info/top_level.txt
mar_eval-0.1.1.dist-info/RECORD
