Metadata-Version: 2.4
Name: mar-eval
Version: 0.1.1
Summary: Task-based evaluation toolkit for Metal Artifact Reduction (MAR) in CT imaging (Annex GG Framework)
Author: Christopher D. Cocchiaraley
License-Expression: MIT
Requires-Python: >=3.9
License-File: LICENSE
Requires-Dist: numpy
Requires-Dist: scipy
Requires-Dist: scikit-learn
Dynamic: license-file
